heyfour/VERSION
heyfour/__init__.py
heyfour/py.typed
heyfour-1.0.0a1.dist-info/LICENSE
heyfour-1.0.0a1.dist-info/METADATA
heyfour-1.0.0a1.dist-info/WHEEL
heyfour-1.0.0a1.dist-info/top_level.txt
heyfour-1.0.0a1.dist-info/RECORD
