Metadata-Version: 2.1
Name: heyfour
Version: 1.0.0a1
Summary: Paper size calculator
Home-page: https://heyfour.dev
Author: Cariad Eccleston
Author-email: cariad@cariad.earth
License: MIT
Project-URL: Documentation, https://heyfour.dev
Project-URL: Funding, https://github.com/sponsors/cariad
Project-URL: Issues, https://github.com/cariad/heyfour/issues
Project-URL: Source, https://github.com/cariad/heyfour
Classifier: Development Status :: 3 - Alpha
Classifier: License :: OSI Approved :: MIT License
Classifier: Natural Language :: English
Classifier: Operating System :: OS Independent
Classifier: Programming Language :: Python :: 3 :: Only
Classifier: Programming Language :: Python :: 3.10
Classifier: Programming Language :: Python :: 3.11
Classifier: Programming Language :: Python :: 3.9
Classifier: Typing :: Typed
Requires-Python: >=3.9
License-File: LICENSE
